ruleboost.py
ruleboost-0.4.0.dist-info/licenses/LICENSE
ruleboost-0.4.0.dist-info/METADATA
ruleboost-0.4.0.dist-info/WHEEL
ruleboost-0.4.0.dist-info/top_level.txt
ruleboost-0.4.0.dist-info/RECORD
