Metadata-Version: 2.4
Name: ruleboost
Version: 0.4.0
Summary: Efficient interpretable rule ensemble learning via gradient boosting implemented with numba.
Author-email: Mario Boley <mario.boley@gmail.com>, Fan Yang <fan.yang1@monash.edu>
License-Expression: MIT
License-File: LICENSE
Requires-Dist: numpy<2.3,>=2.2.6
Requires-Dist: scipy<1.16,>=1.15.3
Requires-Dist: numba<1.0,>=0.61.2
Requires-Dist: scikit-learn<2.0,>=1.7.0
Requires-Dist: optikon<0.4,==0.3.0
Dynamic: license-file
